waveform_factory/__init__.py
waveform_factory/pattern_generator.py
waveform_factory/patterns/__init__.py
waveform_factory/patterns/arches.py
waveform_factory/patterns/autoregressive.py
waveform_factory/patterns/cosine.py
waveform_factory/patterns/decay.py
waveform_factory/patterns/exponential.py
waveform_factory/patterns/gaussian_noise.py
waveform_factory/patterns/half_rectified_wave.py
waveform_factory/patterns/morlet.py
waveform_factory/patterns/rate.py
waveform_factory/patterns/sawtooth.py
waveform_factory/patterns/sine.py
waveform_factory/patterns/square.py
waveform_factory/patterns/step.py
waveform_factory/patterns/stepped.py
waveform_factory/patterns/triangle.py
waveform_factory/utils/__init__.py
waveform_factory/utils/helpers.py
waveform_factory-0.1.3.dist-info/LICENSE
waveform_factory-0.1.3.dist-info/METADATA
waveform_factory-0.1.3.dist-info/WHEEL
waveform_factory-0.1.3.dist-info/top_level.txt
waveform_factory-0.1.3.dist-info/RECORD
