Metadata-Version: 2.1
Name: waveform-factory
Version: 0.1.3
Summary: Wave form data generator
Home-page: https://github.com/MrB-Can/waveform-factory
Author: Paul Bennett
Author-email: paul@lgis.ca
License: UNKNOWN
Platform: UNKNOWN
License-File: LICENSE
Requires-Dist: numpy (>=1.25.1)
Requires-Dist: matplotlib (>=3.7.2)
Requires-Dist: scipy (>=1.11.1)
